[
  {
    "ContainingType": "Product_APIs.Controllers.ProductController",
    "Method": "GetAllProduct",
    "RelativePath": "api/Product",
    "HttpMethod": "GET",
    "IsController": true,
    "Order": 0,
    "Parameters": [],
    "ReturnTypes": []
  },
  {
    "ContainingType": "Product_APIs.Controllers.ProductController",
    "Method": "AddProduct",
    "RelativePath": "api/Product",
    "HttpMethod": "POST",
    "IsController": true,
    "Order": 0,
    "Parameters": [
      {
        "Name": "addProductDTO",
        "Type": "Product_APIs.Model.AddProductDTO",
        "IsRequired": true
      }
    ],
    "ReturnTypes": []
  },
  {
    "ContainingType": "Product_APIs.Controllers.ProductController",
    "Method": "GetProductById",
    "RelativePath": "api/Product/{id}",
    "HttpMethod": "GET",
    "IsController": true,
    "Order": 0,
    "Parameters": [
      {
        "Name": "id",
        "Type": "System.Int32",
        "IsRequired": true
      }
    ],
    "ReturnTypes": []
  },
  {
    "ContainingType": "Product_APIs.Controllers.ProductController",
    "Method": "UpdateProduct",
    "RelativePath": "api/Product/{id}",
    "HttpMethod": "PUT",
    "IsController": true,
    "Order": 0,
    "Parameters": [
      {
        "Name": "id",
        "Type": "System.Int32",
        "IsRequired": true
      },
      {
        "Name": "updateProductDTO",
        "Type": "Product_APIs.Model.UpdateProductDTO",
        "IsRequired": true
      }
    ],
    "ReturnTypes": []
  },
  {
    "ContainingType": "Product_APIs.Controllers.ProductController",
    "Method": "DeleteProduct",
    "RelativePath": "api/Product/{id}",
    "HttpMethod": "DELETE",
    "IsController": true,
    "Order": 0,
    "Parameters": [
      {
        "Name": "id",
        "Type": "System.Int32",
        "IsRequired": true
      }
    ],
    "ReturnTypes": []
  }
]